pypi_pdm_template-0.1.6.dist-info/METADATA
pypi_pdm_template-0.1.6.dist-info/WHEEL
pypi_pdm_template-0.1.6.dist-info/licenses/LICENSE
pypi_pdm_template/__init__.py
pypi_pdm_template/__main__.py
pypi_pdm_template/gui/__init__.py
pypi_pdm_template/gui/main.py
pypi_pdm_template/utils/__init__.py
pypi_pdm_template-0.1.6.dist-info/RECORD
