Metadata-Version: 2.1
Name: pypi_pdm_template
Version: 0.1.6
Summary: a template for build python package to upload pypi repository bu using pdm
Author-Email: lgf4591 <lgf4591@outlook.com>
License: MIT License
Project-URL: Home, https://github.com/lgf4591/pypi_pdm_template
Project-URL: Changelog, https://github.com/lgf4591/pypi_pdm_template/blob/main/CHANGELOG.md
Project-URL: Docs, https://github.com/lgf4591/pypi_pdm_template/blob/main/README.md#yapf
Project-URL: Issues, https://github.com/lgf4591/pypi_pdm_template/issues
Requires-Python: >=3.9
